dwollav2/__init__.py
dwollav2/auth.py
dwollav2/client.py
dwollav2/error.py
dwollav2/response.py
dwollav2/token.py
dwollav2/version.py
dwollav2-2.3.0.dist-info/LICENSE.txt
dwollav2-2.3.0.dist-info/METADATA
dwollav2-2.3.0.dist-info/WHEEL
dwollav2-2.3.0.dist-info/top_level.txt
dwollav2-2.3.0.dist-info/RECORD
